Workbook

Sheet Hypotheses
A1: HYPOTHÈSES - ACQUISITION BRICORAMA FRANCE
A3: 1. DONNÉES DE L'ANNÉE DE BASE (N = 2024)
A4: Chiffre d'Affaires (CA_N) | B4: 500000000 | C4: €
A5: EBE (EBE_N) | B5: 40000000 | C5: €
A6: Résultat d'Exploitation (EBIT_N) | B6: 30000000 | C6: €
A7: BFR (BFR_N) | B7: 50000000 | C7: €
A8: Capex (Capex_N) | B8: 12000000 | C8: €
A9: Dettes financières totales | B9: 80000000 | C9: €
A10: Trésorerie | B10: 10000000 | C10: €
A12: 2. TAUX ET HYPOTHÈSES DE CROISSANCE
A13: Taux d'impôt sur les sociétés | B13: 0.25
A14: Taux d'actualisation (WACC) | B14: 0.08
A15: Taux de croissance du volume | B15: 0.05
A16: Taux d'inflation prix de vente | B16: 0.05
A17: Taux d'inflation coûts | B17: 0.05
A18: Horizon de projection (années) | B18: 5 | C18: ans
A19: Taux de croissance long terme (g_inf) | B19: 0.02
A20: Multiple EBE pour dette max | B20: 3.5 | C20: x
A21: Taux dette senior | B21: 0.05
A23: 3. RATIOS CALCULÉS (FORMULES)
A24: Marge EBE (EBE/CA) | B24: =B5/B4 | C24: Formule: EBE_N / CA_N
A25: Marge EBIT (EBIT/CA) | B25: =B6/B4 | C25: Formule: EBIT_N / CA_N
A26: Ratio Capex/CA | B26: =B8/B4 | C26: Formule: Capex_N / CA_N
A27: Ratio BFR/CA | B27: =B7/B4 | C27: Formule: BFR_N / CA_N
A28: Croissance nominale CA | B28: =(1+B15)*(1+B16)-1 | C28: Formule: (1+g_vol)*(1+g_prix)-1
A29: Dette nette | B29: =B9-B10 | C29: Formule: Dettes - Trésorerie

Sheet Calculs_DCF
A1: PROJECTION DES FLUX DE TRÉSORERIE (DCF) - 5 ANS
A3: Poste | B3: Année N (Base) | C3: N+1 | D3: N+2 | E3: N+3 | F3: N+4 | G3: N+5
A4: Chiffre d'Affaires (CA) | B4: =Hypotheses!B4 | C4: =B4*(1+Hypotheses!$B$28) | D4: =C4*(1+Hypotheses!$B$28) | E4: =D4*(1+Hypotheses!$B$28) | F4: =E4*(1+Hypotheses!$B$28) | G4: =F4*(1+Hypotheses!$B$28)
A5: Croissance CA (%) | B5: - | C5: =(C4-B4)/B4 | D5: =(D4-C4)/C4 | E5: =(E4-D4)/D4 | F5: =(F4-E4)/E4 | G5: =(G4-F4)/F4
A6: EBE (EBITDA) | B6: =Hypotheses!B5 | C6: =C4*Hypotheses!$B$24 | D6: =D4*Hypotheses!$B$24 | E6: =E4*Hypotheses!$B$24 | F6: =F4*Hypotheses!$B$24 | G6: =G4*Hypotheses!$B$24
A7: Marge EBE (%) | B7: =B6/B4 | C7: =C6/C4 | D7: =D6/D4 | E7: =E6/E4 | F7: =F6/F4 | G7: =G6/G4
A8: Résultat d'Exploitation (EBIT) | B8: =Hypotheses!B6 | C8: =C4*Hypotheses!$B$25 | D8: =D4*Hypotheses!$B$25 | E8: =E4*Hypotheses!$B$25 | F8: =F4*Hypotheses!$B$25 | G8: =G4*Hypotheses!$B$25
A9: - Impôt sur Sociétés (25%) | B9: =B8*Hypotheses!$B$13 | C9: =C8*Hypotheses!$B$13 | D9: =D8*Hypotheses!$B$13 | E9: =E8*Hypotheses!$B$13 | F9: =F8*Hypotheses!$B$13 | G9: =G8*Hypotheses!$B$13
A10: + Dotations Amort. (EBITDA-EBIT) | B10: =B6-B8 | C10: =C6-C8 | D10: =D6-D8 | E10: =E6-E8 | F10: =F6-F8 | G10: =G6-G8
A11: - Investissements (Capex) | B11: =Hypotheses!B8 | C11: =C4*Hypotheses!$B$26 | D11: =D4*Hypotheses!$B$26 | E11: =E4*Hypotheses!$B$26 | F11: =F4*Hypotheses!$B$26 | G11: =G4*Hypotheses!$B$26
A12: BFR (stock) | B12: =Hypotheses!B7 | C12: =C4*Hypotheses!$B$27 | D12: =D4*Hypotheses!$B$27 | E12: =E4*Hypotheses!$B$27 | F12: =F4*Hypotheses!$B$27 | G12: =G4*Hypotheses!$B$27
A13: - Variation de BFR | B13: - | C13: =C12-B12 | D13: =D12-C12 | E13: =E12-D12 | F13: =F12-E12 | G13: =G12-F12
A15: =Flux de Trésorerie Disponible (FCF) | B15: - | C15: =C6-C9-C13-C11 | D15: =D6-D9-D13-D11 | E15: =E6-E9-E13-E11 | F15: =F6-F9-F13-F11 | G15: =G6-G9-G13-G11
A18: ACTUALISATION DES FLUX
A19: Année | C19: 1 | D19: 2 | E19: 3 | F19: 4 | G19: 5
A20: Facteur d'actualisation | B20: - | C20: =1/(1+Hypotheses!$B$14)^C19 | D20: =1/(1+Hypotheses!$B$14)^D19 | E20: =1/(1+Hypotheses!$B$14)^E19 | F20: =1/(1+Hypotheses!$B$14)^F19 | G20: =1/(1+Hypotheses!$B$14)^G19
A21: FCF Actualisé | B21: - | C21: =C15*C20 | D21: =D15*D20 | E21: =E15*E20 | F21: =F15*F20 | G21: =G15*G20

Sheet Valorisation
A1: VALORISATION DE L'ENTREPRISE
A3: 1. VAN DES FLUX DE TRÉSORERIE
A4: Somme des FCF actualisés (5 ans) | B4: =SUM(Calculs_DCF!C21:G21) | C4: € | D4: Formule: Σ FCF_actualisé
A6: 2. VALEUR TERMINALE
A7: FCF année 5 (FCF_T) | B7: =Calculs_DCF!G15 | C7: €
A8: FCF année 6 (FCF_T+1) | B8: =B7*(1+Hypotheses!B19) | C8: € | D8: Formule: FCF_T × (1 + g_inf)
A9: Valeur Terminale (non actualisée) | B9: =B8/(Hypotheses!B14-Hypotheses!B19) | C9: € | D9: Formule: FCF_T+1 / (WACC - g_inf)
A10: Valeur Terminale Actualisée | B10: =B9/((1+Hypotheses!B14)^Hypotheses!B18) | C10: € | D10: Formule: VT / (1+WACC)^5
A12: 3. VALEUR D'ENTREPRISE
A13: VALEUR D'ENTREPRISE (VE) | B13: =B4+B10 | C13: € | D13: Formule: VAN_FCF + VT_actualisée
A15: 4. VALEUR DES TITRES (EQUITY VALUE)
A16: Dette nette | B16: =Hypotheses!B29 | C16: €
A17: VALEUR DES TITRES | B17: =B13-B16 | C17: € | D17: Formule: VE - Dette nette
A19: 5. CAPACITÉ D'ENDETTEMENT ET APPORT EN CAPITAL
A20: EBE moyen prévisionnel | B20: =AVERAGE(Calculs_DCF!C6:G6) | C20: €
A21: Multiple EBE | B21: =Hypotheses!B20 | C21: x
A22: Dette maximale | B22: =B20*B21 | C22: € | D22: Formule: EBE_moy × Multiple
A23: APPORT EN CAPITAL MINIMUM | B23: =MAX(0,B17-B22) | C23: € | D23: Formule: MAX(0, Val_titres - Dette_max)

Sheet Budget_Tresorerie
A1: BUDGET DE TRÉSORERIE DE LA HOLDING
A3: PARAMÈTRES DE LA DETTE SENIOR
A4: Dette Senior contractée | B4: =MIN(Valorisation!B22,Valorisation!B17) | C4: € | D4: Formule: MIN(Dette_max, Val_titres)
A5: Taux d'intérêt annuel | B5: =Hypotheses!B21
A6: Durée de remboursement | B6: =Hypotheses!B18 | C6: ans
A7: Remboursement annuel du principal | B7: =B4/B6 | C7: € | D7: Formule: Dette / Durée (linéaire)
A9: Élément | B9: N+1 | C9: N+2 | D9: N+3 | E9: N+4 | F9: N+5
A10: Trésorerie début de période | B10: =Valorisation!B23 | C10: =B14 | D10: =C14 | E10: =D14 | F10: =E14
A11: + FCF remonté de la cible | B11: =Calculs_DCF!C15 | C11: =Calculs_DCF!D15 | D11: =Calculs_DCF!E15 | E11: =Calculs_DCF!F15 | F11: =Calculs_DCF!G15
A12: - Intérêts dette senior | B12: =$B$4*$B$5 | C12: =($B$4-$B$7)*$B$5 | D12: =($B$4-2*$B$7)*$B$5 | E12: =($B$4-3*$B$7)*$B$5 | F12: =($B$4-4*$B$7)*$B$5
A13: - Remboursement principal | B13: =$B$7 | C13: =$B$7 | D13: =$B$7 | E13: =$B$7 | F13: =$B$7
A14: =Trésorerie fin de période | B14: =B10+B11-B12-B13 | C14: =C10+C11-C12-C13 | D14: =D10+D11-D12-D13 | E14: =E10+E11-E12-E13 | F14: =F10+F11-F12-F13
A17: DETTE RESTANTE
A18: Dette restante fin de période | B18: =$B$4-$B$7 | C18: =$B$4-2*$B$7 | D18: =$B$4-3*$B$7 | E18: =$B$4-4*$B$7 | F18: =$B$4-5*$B$7

Sheet Ratios_Analyse
A1: RATIOS D'ANALYSE FINANCIÈRE
A3: Ces ratios doivent être calculés à partir des comptes annuels réels de Bricorama
A5: Ratio | B5: Formule | C5: 2022 | D5: 2023 | E5: 2024
A6: Liquidité Générale | B6: Actif Circulant / Passif Circulant
A7: Liquidité Réduite | B7: (Actif Circ. - Stocks) / Passif Circ.
A8: Autonomie Financière | B8: Capitaux Propres / Total Passif
A9: Ratio Dettes/EBE | B9: Dettes Financières / EBE
A10: Rentabilité économique (ROA) | B10: EBIT / Total Actif
A11: Rentabilité financière (ROE) | B11: Résultat Net / Capitaux Propres
A12: Marge nette | B12: Résultat Net / CA
A13: Rotation des actifs | B13: CA / Total Actif
